testil.py
testil-1.1.dist-info/METADATA
testil-1.1.dist-info/WHEEL
testil-1.1.dist-info/top_level.txt
testil-1.1.dist-info/RECORD
